Flask_RESTive_Identifiers-0.0.3.dist-info/DESCRIPTION.rst
Flask_RESTive_Identifiers-0.0.3.dist-info/METADATA
Flask_RESTive_Identifiers-0.0.3.dist-info/RECORD
Flask_RESTive_Identifiers-0.0.3.dist-info/WHEEL
Flask_RESTive_Identifiers-0.0.3.dist-info/metadata.json
Flask_RESTive_Identifiers-0.0.3.dist-info/top_level.txt
flask_restive_identifiers/__init__.py
flask_restive_identifiers/schemas.py
flask_restive_identifiers/services.py
flask_restive_identifiers/utils.py
