Metadata-Version: 2.0
Name: Flask-RESTive-Identifiers
Version: 0.0.3
Summary: Flask-RESTive extension to work with identifiers.
Home-page: https://github.com/left-join/flask-restive-identifiers
Author: left-join
Author-email: left-join@riseup.net
License: MIT
Download-URL: https://github.com/left-join/flask-restive-identifiers.git
Keywords: Flask-RESTive,generate,id
Platform: any
Classifier: Environment :: Web Environment
Classifier: Intended Audience :: Developers
Classifier: License :: OSI Approved :: MIT License
Classifier: Operating System :: OS Independent
Classifier: Programming Language :: Python
Classifier: Topic :: Internet :: WWW/HTTP :: Dynamic Content
Classifier: Topic :: Software Development :: Libraries :: Python Modules
Requires-Dist: flask-restive (>=0.0.2)
Requires-Dist: sqlalchemy (>=1.1.13)
Requires-Dist: sqlalchemy-utils (>=0.32.12)
Requires-Dist: psycopg2 (>=2.7.3.1)
